MANIFEST.in
README.md
setup.py
witokit/__init__.py
witokit/main.py
witokit.egg-info/PKG-INFO
witokit.egg-info/SOURCES.txt
witokit.egg-info/dependency_links.txt
witokit.egg-info/entry_points.txt
witokit.egg-info/not-zip-safe
witokit.egg-info/requires.txt
witokit.egg-info/top_level.txt
witokit/exceptions/__init__.py
witokit/exceptions/method.py
witokit/exceptions/parameter.py
witokit/logging/__init__.py
witokit/logging/logging.yml
witokit/utils/__init__.py
witokit/utils/config.py
witokit/utils/constants.py
witokit/utils/files.py
witokit/utils/immutables.py
witokit/utils/urls.py