Metadata-Version: 2.1
Name: witokit
Version: 0.1.14
Summary: A python module to generate a tokenized dump of Wikipedia for NLP
Home-page: https://github.com/akb89/witokit
Author: Alexandre Kabbach
Author-email: akb@3azouz.net
License: MIT
Download-URL: https://pypi.org/project/witokit/#files
Keywords: wikipedia,dump,tokenization,nlp
Platform: any
Classifier: Development Status :: 4 - Beta
Classifier: Environment :: Console
Classifier: Intended Audience :: Developers
Classifier: Intended Audience :: Education
Classifier: Intended Audience :: Science/Research
Classifier: License :: OSI Approved :: MIT License
Classifier: Natural Language :: English
Classifier: Operating System :: OS Independent
Classifier: Programming Language :: Python :: 3.5
Classifier: Programming Language :: Python :: 3.6
Classifier: Programming Language :: Python :: 3.7
Classifier: Topic :: Scientific/Engineering :: Artificial Intelligence
Classifier: Topic :: Software Development :: Libraries :: Python Modules
Classifier: Topic :: Text Processing :: Linguistic
